aiofortnite/__init__.py
aiofortnite/abc.py
aiofortnite/caches.py
aiofortnite/client.py
aiofortnite/selfrenewingtokens.py
aiofortnite/urls.py
aiofortnite-0.53.dist-info/METADATA
aiofortnite-0.53.dist-info/RECORD
aiofortnite-0.53.dist-info/WHEEL
aiofortnite-0.53.dist-info/top_level.txt
