Metadata-Version: 2.1
Name: aiofortnite
Version: 0.53
Summary: A asyncio wrapper for Fortnite.
Home-page: https://github.com/JakeMakesStuff/aiofortnite
Author: Jake Gealer
Author-email: jake@gealer.email
License: MPL-2.0
Platform: UNKNOWN
Classifier: License :: OSI Approved :: Mozilla Public License 2.0 (MPL 2.0)
Classifier: Programming Language :: Python
Classifier: Programming Language :: Python :: 3.5
Classifier: Programming Language :: Python :: 3.6
Classifier: Programming Language :: Python :: Implementation :: CPython
Classifier: Programming Language :: Python :: Implementation :: PyPy
Requires-Python: >=3.5.3
Requires-Dist: aiohttp
